[
    {
        "titulo": "Alerta Ciudadana: Una nueva forma de combatir el delito",
        "archivo": "0B0UxvnUHVKBcaTFEbng1YmYxTWc",
        "categoria":"Trabajos de Alumnos",
        "tipo": "poster",
        "Autores": [
            {
                "Autor": "Díaz Lederhos, Nahuel Matias"
            },
            {
                "Autor": "Gelatti, Facundo Javier"
            },
            {
                "Autor": "Martin, Rodrigo Alexander"
            },
            {
                "Autor": "Martinez Roitman, Aldana Milena"
            },
            {
                "Autor": "Mendez Utz, Andrés Pelayo"
            }
        ]
    },
{
        "titulo": "Análisis de puestos de sistemas de información",
        "archivo": "0B0UxvnUHVKBcdEEwNUF3bGpKdDQ",
        "categoria":"Trabajos de Alumnos",
        "tipo": "poster",
        "Autores": [
            {
                "Autor": "Ivan Arnaudo"
            },
            {
                "Autor": "Tomas Gullón"
            }
        ]
    },
    {
        "titulo": "Análisis en tiempo de ejecución para detección de problemas de seguridad de Javascript del lado del servidor",
        "archivo": "0B0UxvnUHVKBcdFRPODlFeW5RM1k",
        "categoria":"Trabajos de Alumnos",
        "tipo": "poster",
        "Autores": [
            {
                "Autor": "Carlos Alejandro Ryser"
            }
        ]
    },
    {
        "titulo": "Analisis y gestión de riesgos en la simulacion de vuelo",
        "archivo": "0B0UxvnUHVKBcOERJTi16a2REQjQ",
        "categoria":"Trabajos de Alumnos",
        "tipo": "poster",
        "Autores": [
            {
                "Autor": "Amigo Barzola, Mailen"
            },
            {
                "Autor": "Vazquez Petrini, Santiago "
            }
        ]
    },

    {
        "titulo": "Aplicación de Big Data para el análisis de accidentes viales",
        "archivo": "0B0UxvnUHVKBcUGc2RUxtclpackU",
        "categoria":"Trabajos de Alumnos",
        "tipo": "poster",
        "Autores": [
            {
                "Autor": "Romina Nicastro"
            },
            {
                "Autor": "Aldana Yael Vaca"
            }
        ]
    },
    {
        "titulo": "Aplicación de chat para alertas a destacamentos de bomberos basado en posicionamiento georeferencial",
        "archivo": "0B0UxvnUHVKBcbnhTR2I3c1FVcTQ",
        "categoria":"Trabajos de Alumnos",
        "tipo": "poster",
        "Autores": [
            {
                "Autor": "Martín A. Navarro Mugas"
            },
            {
                "Autor": "Marina Cardenas"
            },
            {
                "Autor":"Julio Castillo"
            }
        ]
 },
    {
        "titulo": "Aplicación de Sistemas Embebidos para Determinar la Actitud",
        "archivo": "0B0UxvnUHVKBcMm1VdzlVZUNON1U",
        "categoria":"Trabajos de Alumnos",
        "tipo": "poster",
        "Autores": [
            {
                "Autor": "Carlos N. Oviedo"
            },
            {
                "Autor": "Yamil E. Zimmermann"
            },
            {
                "Autor": "Luis G. Hintz"
            },
            {
                "Autor": "Daniel N. Turra"
            },
            {
                "Autor": "Juan J. Gaspanello"
            }
        ]
    },
    {
        "titulo": "Aplicacion de un Algoritmo Genetico para determinar las caracteristicas de un estudiante universitario que permiten alcanzar un rendimiento académico óptimo",
        "archivo": "0B0UxvnUHVKBca2U5VGMtNmdLTWc",
        "categoria":"Trabajos de Alumnos",
        "tipo": "poster",
        "Autores": [
            {
                "Autor": "Anahí Bezel"
            },
            {
                "Autor": "Sofía De Winne"
            },
            {
                "Autor": "Florencia Reales"
            },
            {
                "Autor": "Rodrigo Vargas"
            }
        ]
    },
    {
        "titulo": "Aplicación embebida para control de parámetros temperatura e iluminación",
        "archivo": "0B0UxvnUHVKBcdV9ZTTdBallfcjA",
        "categoria":"Trabajos de Alumnos",
        "tipo": "poster",
        "Autores": [
            {
                "Autor": "Erik Hromek"
            },
            {
                "Autor": "Jorge Osio"
            },
            {
                "Autor": "Diego Montezanti"
            },
            {
                "Autor": "Martín Morales"
            }
        ]
    },
    {
        "titulo": "Aplicación móvil que ayude al proceso de enseñanza y aprendizaje en la asignatura de sistemas y organizaciones de la carrera de Ingeniería en Sistemas de Información",
        "archivo": "0B0UxvnUHVKBcZ3U4dWctS09wd0E",
        "categoria":"Trabajos de Docentes - Investigadores",
        "tipo": "poster",
        "Autores": [
            {
                "Autor": "Sebastián Plawner"
            },
            {
                "Autor": "Agustín Pividori"
            },
            {
                "Autor": "Ariel Deroche"
            },
            {
                "Autor": "Cinthia Vegega"
            },
            {
                "Autor": "Pablo Pytel "
            },
            {
                "Autor": "Luciano Straccia"
            },
            {
                "Autor": "M. Florencia Pollo-Cattaneo"
            }
        ]
    },
    {
        "titulo": "Artachito: Cesto de basura inteligente",
        "archivo": "0B0UxvnUHVKBcOFRyb3A2THVBWVk",
        "categoria":"Trabajos de Alumnos",
        "tipo": "poster",
        "Autores": [
            {
                "Autor": "Adrián Eduardo Elías"
            },
            {
                "Autor": "Sebastián Tempone"
            },
            {
                "Autor": "Sebastián Stefanetti"
            }
        ]
    },
    {
        "titulo": "Big Data y privacidad del individuo",
        "archivo": "0B0UxvnUHVKBceU5waHdYVUV4dXM",
        "categoria":"Trabajos de Alumnos",
        "tipo": "poster",
        "Autores": [
            {
                "Autor": "Carrozzo Eduardo"
            },
            {
                "Autor": "Comparín Julieta "
            }
        ]
 },


    {
        "titulo": "Clasificación Automática de Textos aplicados a textos periodísticos del noroeste argentino",
        "archivo": "0B0UxvnUHVKBcR3ZsR2JXcy1fQkE",
        "categoria":"Trabajos de Alumnos",
        "tipo": "poster",
        "Autores": [
            {
                "Autor": "Juan Gabriel Salinas "
            }
        ]
    },
{
        "titulo": "Combinando Fuerzas BI + IOT",
        "archivo": "0B0UxvnUHVKBcRWxwU1lwSnBsSVE",
        "categoria":"Trabajos de Alumnos",
        "tipo": "poster",
        "Autores": [
            {
                "Autor": "Emiliano Barco "
            }
        ]
 },
 {
        "titulo": "Contribución de las TICs en la Cadena de Valor para el Desarrollo Industrial",
        "archivo": "0B0UxvnUHVKBcSFI5TnRMdnZaR00",
        "categoria":"Trabajos de Docentes - Investigadores",
        "tipo": "poster",
        "Autores": [
            {
                "Autor": "Alicia Mon"
            },
            {
                "Autor": "Horacio Del Giorgio"
            },
            {
                "Autor": "Eduardo De María"
            },
            {
                "Autor": "Claudia Figuerola"
            },
            {
                "Autor": "Matías Querel"
            }

        ]
 },

    {
        "titulo": "Control de Calidad en una Línea de Producción mediante Análisis de Imágenes",
        "archivo": "0B0UxvnUHVKBcV1R6LUxkUUs1d3c",
        "categoria":"Trabajos de Docentes - Investigadores",
        "tipo": "poster",
        "Autores": [
            {
                "Autor": "Esp. Lic. Sergio Daniel Conde"
            },
            {
                "Autor": "Ing. Osvaldo Marcovecchio"
            }
        ]
    },
{
        "titulo": "Deep Learning y Web Semantica",
        "archivo": "0B0UxvnUHVKBcMnpLQmdMc0JSdnM",
        "categoria":"Trabajos de Alumnos",
        "tipo": "poster",
        "Autores": [
            {
                "Autor": "Arrúa, Martín Nahuel "
            },
            {
                "Autor": "Mannise Nerón, María Agustina "
            },
            {
                "Autor":"Rivera, Ramiro Adolfo "
            }
        ]
 },
 {
        "titulo": "Definir un Equipo de Futbol Optimo mediante RNA",
        "archivo": "0B0UxvnUHVKBcN2NacWZyUlBIUUU",
        "categoria":"Trabajos de Alumnos",
        "tipo": "poster",
        "Autores": [
            {
                "Autor": "Lucas Cariddi"
            },
            {
                "Autor": "Federico Alvarez"
            },
            {
                "Autor":"José Evaristo Marro"
            }
        ]
 },

    {
        "titulo": "Desarollo de aplicaciones de realidad aumentada para practicas en escuelas de nivel primario",
        "archivo": "0B0UxvnUHVKBcSnIwWm92X0lVQXM",
        "categoria":"Trabajos de Alumnos",
        "tipo": "poster",
        "Autores": [
            {
                "Autor": "Mariela Alejandra Calisaya"
            },
            {
                "Autor": "Brenda Veramendi"
            }
        ]
    },
    {
        "titulo": "Desarrollo de Software Educativo en un Entorno Cliente - Servidor",
        "archivo": "0B0UxvnUHVKBcYmstejVGbHU2QlU",
        "categoria":"Trabajos de Alumnos",
        "tipo": "poster",
        "Autores": [
            {
                "Autor": "Martín Oscar Ganami"
            },
            {
                "Autor": "Héctor Liberatori"
            }
        ]
    },
    {
        "titulo": "Desarrollo de un Modelo de Procesos para Selección de Bases de Datos ante Problemáticas Determinadas",
        "archivo": "0B0UxvnUHVKBcTk1Pc1JVczFzVnc",
        "categoria":"Trabajos de Docentes - Investigadores",
        "tipo": "poster",
        "Autores": [
            {
                "Autor": "Giovanni Rottoli"
            },
            {
                "Autor": "Patricio Boffino"
            },
            {
                "Autor": "Martín Mihura"
            },
            {
                "Autor": "Juan Zaffaroni"
            },
            {
                "Autor":"Ma. Florencia Pollo-Cattaneo"
            }
        ]
    },
    {
        "titulo": "Descripción y comparación de las diferentes tecnologías de interfaz cerebro computador",
        "archivo": "0B0UxvnUHVKBcMnRXeUlNQlhMMU0",
        "categoria":"Trabajos de Alumnos",
        "tipo": "poster",
        "Autores": [
            {
                "Autor": "Delucchi, Pablo "
            },
            {
                "Autor": "Duarte, Gastón "
            },
            {
                "Autor": "Di Chena, Federico "
            },
            {
                "Autor": "Ramirez, Gabriel "
            },
            {
                "Autor": "Giovanetti, Rodrigo "
            },
            {
                "Autor": "Pacherres, Adrián "
            }
        ]
 },
    {
        "titulo": "Detector de actividades en una memoria USB",
        "archivo": "0B0UxvnUHVKBcbzFCWGtNVEppNlU",
        "categoria":"Trabajos de Alumnos",
        "tipo": "poster",
        "Autores": [
            {
                "Autor": "Genaro Franceschelli "
            },
            {
                "Autor": "Milagros Zea Cárdenas "
            }
        ]
    },
    {
        "titulo": "Diagnóstico poligráfico de la verdad mediante inteligencia artifial",
        "archivo": "0B0UxvnUHVKBcM0kxSFUzdzdlOXM",
        "categoria":"Trabajos de Alumnos",
        "tipo": "poster",
        "Autores": [
            {
                "Autor": "Ignacio Agustín Casais "
            },
            {
                "Autor": "Natalia Serebrinsky "
            }
        ]
 },
 {
        "titulo": "Diseño de Lanzador con Interfaz Intuitiva para la Tercera Edad en Dispositivos Móviles Android",
        "archivo": "0B0UxvnUHVKBcR1NNZ0lMRW82d1k",
        "categoria":"Trabajos de Alumnos",
        "tipo": "poster",
        "Autores": [
            {
                "Autor": "Sebastián Plawner "
            },
            {
                "Autor": "Germán Claudio Novoa "
            },
            {
                "Autor": "Demian Iacono "
            },
            {
                "Autor": "Martín Saposnic"
            }
        ]
 },  
    
    {
        "titulo": "Diseño de prototipo de un sistema de monitoreo y control anti incendios",
        "archivo": "0B0UxvnUHVKBcaG9TY25xWmJfZzA",
        "categoria":"Trabajos de Alumnos",
        "tipo": "poster",
        "Autores": [
            {
                "Autor": "Marco Mallorquín "
            },
            {
                "Autor": "Dercio Pareja "
            }
        ]
    },
{
        "titulo": "Distintos tipos de aplicaciones de Seguridad (Biometria)",
        "archivo": "0B0UxvnUHVKBcSzNDMUdtMFZhU0k",
        "categoria":"Trabajos de Alumnos",
        "tipo": "poster",
        "Autores": [
            {
                "Autor": "Agustín Moles"
            },
            {
                "Autor": "Ezequiel Bianchetta"
            },
             {
                "Autor": "Melanie Ibañez"
            },
            {
                "Autor": "Sergio Vásquez"
            }
        ]
 },
 {
        "titulo": "Draw Your Fish Bone",
        "archivo": "0B0UxvnUHVKBcOGwyUFVsUVdPNHM",
        "categoria":"Trabajos de Alumnos",
        "tipo": "poster",
        "Autores": [
            {
                "Autor": "Nicolás Abatedaga "
            }
        ]
 },

    {
        "titulo": "El ingeniero en sistemas de información y la gestión tecnológico educativa",
        "archivo": "0B0UxvnUHVKBcS09oZF84ajFSdzQ",
        "categoria":"Trabajos de Docentes - Investigadores",
        "tipo": "poster",
        "Autores": [
            {
                "Autor": "Odetti, María Alejandra"
            },
            {
                "Autor": "Kabusch, Andrés Ricard"
            }
        ]
    },
{
        "titulo": "Enseñanzas en la implementación de un analizador sintáctico por descenso recursivo",
        "archivo": "0B0UxvnUHVKBcMW1rNmFULXowcW8",
        "categoria":"Trabajos de Docentes - Investigadores",
        "tipo": "poster",
        "Autores": [
            {
                "Autor": "Juan C. Vázquez"
            },
            {
                "Autor": "Leticia E. Constable"
            },
            {
                "Autor": " Wilfredo R. Jornet"
            },
            {
                "Autor": "Brenda E. Meloni "
            },
            {
                "Autor": "Nicolás R. Carballo "
            }
        ]
 },



    {
        "titulo": "Estación inalámbrica basada en microcontroladores para la monitorización del riego en plantaciones de olivo",
        "archivo": "0B0UxvnUHVKBcUHFmaUlxMTMtblk",
        "categoria":"Trabajos de Alumnos",
        "tipo": "poster",
        "Autores": [
            {
                "Autor": "Emmanuel A. Portugal M"
            },
            {
                "Autor": "Fernanda B. Carmona"
            },
            {
                "Autor": "Alberto E. Riba"
            },
            {
                "Autor": "Jorge D. Tejada"
            }
        ]
    },
    {
        "titulo": "Estrategias y Recursos Tecnológicos Para la Creación de Material Didáctico Mediados Por Tic ",
        "archivo": "0B0UxvnUHVKBcQ0pnX2xLOVc1UEU",
        "categoria":"Trabajos de Docentes - Investigadores",
        "tipo": "poster",
        "Autores": [
            {
                "Autor": "Héctor R. Tarifa "
            },
            {
                "Autor": "J. Luis Medina"
            },
            {
                "Autor": "Celia  Torres Bugeau"
            },
            {
                "Autor": "Patricio O. Condorí"
            }
        ]
    },
    {
        "titulo": "Experimentando mas allá de la Realidad",
        "archivo": "0B0UxvnUHVKBcNHkxRlQ4ZEljTUU",
        "categoria":"Trabajos de Alumnos",
        "tipo": "poster",
        "Autores": [
            {
                "Autor": "Lázaro Ansaldi"
            },
            {
                "Autor": "Marcela Dalpra "
            },
            {
                "Autor": "Damián Moreiro"
            }
        ]
    },
    {
        "titulo": "extraccion de información de sitios relacionados a la provincia de Salta",
        "archivo": "0B0UxvnUHVKBcTzlxeEM4Q01FaHc",
        "categoria":"Trabajos de Alumnos",
        "tipo": "poster",
        "Autores": [
            {
                "Autor": "Enzo Rubén Notario"
            }
        ]
    },
    {
        "titulo": "FINDSER, servicios y turnos",
        "archivo": "0B0UxvnUHVKBcR0YzOXBMQXRzNEk",
        "categoria":"Trabajos de Alumnos",
        "tipo": "poster",
        "Autores": [
            {
                "Autor": "Diego Iván Cordoba "
            },
            {
                "Autor": "Carlos Salustiano Escalante "
            },
            {
                "Autor": "Seiyu Ricardo Higa Tamashiro "
            },
            {
                "Autor": "Romina Nicastro "
            },
            {
                "Autor":"Aldana Yael Vaca"
            }
        ]
    },
    {
        "titulo": "Fixit! – Sistema de contrataciones para reparaciones en el hogar",
        "archivo": "0B0UxvnUHVKBcNUVTS2pxQ2lQTUE",
        "categoria":"Trabajos de Alumnos",
        "tipo": "poster",
        "Autores": [
            {
                "Autor": "Francisco Diblasi"
            },
            {
                "Autor": "Germán Antonucci"
            },
            {
                "Autor": "Marco Briganti"
            },
            {
                "Autor": "Gastón Mulé"
            }
        ]
    },
    {
        "titulo": "Framework para Sistema de Reducción de Accidentes de Tráfico en Rutas",
        "archivo": "0B0UxvnUHVKBcYjIxMXNpcVZLeTQ",
        "categoria":"Trabajos de Alumnos",
        "tipo": "poster",
        "Autores": [
            {
                "Autor": "Vanesa Araya "
            },
            {
                "Autor": "Natacha Espada"
            },
            {
                "Autor": "Lucas Leiva"
            },
            {
                "Autor": "Marcelo Tosini"
            }
        ]
    },
    {
        "titulo": "Generación de tests para JavaScript basados en ECMA-262 como primera experiencia de alumnos en un grupo de investigación",
        "archivo": "0B0UxvnUHVKBcTmJFZmhnV3ByUkk",
        "categoria":"Trabajos de Alumnos",
        "tipo": "poster",
        "Autores": [
            {
                "Autor": "Alan Pipino"
            },
            {
                "Autor": "Lucas Astrada"
            }
        ]
    },
    {
        "titulo": "Graficador de fractales complejos",
        "archivo": "0B0UxvnUHVKBcOWZEd2Rma1VqQmc",
        "categoria":"Trabajos de Alumnos",
        "tipo": "poster",
        "Autores": [
            {
                "Autor": "Facundo Javier Gelatti"
            }
        ]
    },
    {
        "titulo": "Green IT como solución al impacto ambiental de la utilización de las tecnologías de la información en las empresas",
        "archivo": "0B0UxvnUHVKBcTmdOUG9Sd2MtOEU",
        "categoria":"Trabajos de Alumnos",
        "tipo": "poster",
        "Autores": [
            {
                "Autor": "Rocío Chipian "
            },
            {
                "Autor": "Nahuel Fleitas "
            },
            {
                "Autor": "Nicolas de Beruti "
            }
        ]
    },
{
        "titulo": "Hardware libre y los nuevos horizontes para la diversidad",
        "archivo": "0B0UxvnUHVKBcT1Q2RzNHQXlLUVU",
        "categoria":"Trabajos de Alumnos",
        "tipo": "poster",
        "Autores": [
            {
                "Autor": "Bertola, Federico Javier "
            },
            {
                "Autor": "Del Valle, Nicolas Gabriel"
            },
            {
                "Autor": "Moreno Ravera, María Alejandra"
            },
            {
                "Autor": "Muñoz Campos, Agustín"
            }
        ]
 },
 {
        "titulo": "Herramienta para la detección temprana de deserción estudiantil para la UTN FRLP Diseño preliminar",
        "archivo": "0B0UxvnUHVKBcelI2b1F1OTZ3NFk",
        "categoria":"Trabajos de Alumnos",
        "tipo": "poster",
        "Autores": [
            {
                "Autor": "Paula Del Giorgio"
            },
            {
                "Autor": "Ismaín Ressel "
            }
        ]
 },

    {
        "titulo": "Herramientas libres aplicadas al testing UTN",
        "archivo": "0B0UxvnUHVKBcWkszMjdleGc3a2M",
        "categoria":"Trabajos de Alumnos",
        "tipo": "poster",
        "Autores": [
            {
                "Autor": "Bertuzzi Gaspari, Augusto "
            },
            {
                "Autor": "Urzagasti, Silvia Liliana "
            }
        ]
    },
    {
        "titulo": "Implementación de Estrategias de apoyo pedagógico",
        "archivo": "0B0UxvnUHVKBcMURmRE03V3RoNEU",
        "categoria":"Trabajos de Docentes - Investigadores",
        "tipo": "poster",
        "Autores": [
            {
                "Autor": "Mirta E. Giovannini"
            },
            {
                "Autor": "Juliana I. Torre"
            }
        ]
    },
    {
        "titulo": "Implementación de GREEN IT en Argentina",
        "archivo": "0B0UxvnUHVKBcRjlSRmFaT01IMFk",
        "categoria":"Trabajos de Alumnos",
        "tipo": "poster",
        "Autores": [
            {
                "Autor": "Agostini Dohmen, Janice"
            },
            {
                "Autor": "Androchuk, Nicolas "
            },
            {
                "Autor": "Aquino, Francisco "
            }
        ]
    },
    {
        "titulo": "Implementación de las impresoras 3D en el ámbito hospitalario",
        "archivo": "0B0UxvnUHVKBcOW5jQnZaeGdmQTA",
        "categoria":"Trabajos de Alumnos",
        "tipo": "poster",
        "Autores": [
            {
                "Autor": "Leandro Enriquez"
            },
            {
                "Autor": "Marcos Blas Pafundi"
            }
        ]
    },
    {
        "titulo": "Implementación efectiva del sistema de gestión SIINAR empleando el enfoque Domain-Drive Design",
        "archivo": "0B0UxvnUHVKBccmJpanNzYXQtZ1U",
        "categoria":"Trabajos de Alumnos",
        "tipo": "poster",
        "Autores": [
            {
                "Autor": "Dana Luz Gonzalez "
            },
            {
                "Autor": "Christian Diego Escalante"
            }
        ]
    },
{
        "titulo": "Inmersión en la Realidad Virtual",
        "archivo": "0B0UxvnUHVKBcV1RzNWRyRVEtT00",
        "categoria":"Trabajos de Alumnos",
        "tipo": "poster",
        "Autores": [
            {
                "Autor": "Alexis Polak "
            },
            {
                "Autor": "Lucas Mazalán "
            },
            {
                "Autor": "Ramiro Colombo "
            },
            {
                "Autor": "Gabriel Barrera "
            }
        ]
 },

 {
        "titulo": "Integrando trayectos curriculares con robótica aplicada, una experiencia en primer año",
        "archivo": "0B0UxvnUHVKBcWlRwX2xHdjR0Vmc",
         "categoria":"Trabajos de Alumnos",
        "tipo": "poster",
        "Autores": [
            {
                "Autor": "Gabina Luz Bianchi "
            },
            {
                "Autor": "Federico Rossi "
            },
            {
                "Autor": "Lucio Bassanti "
            },
            {
                "Autor": "Guillermo Rodriguez"
            }
        ]
    },
    {
        "titulo": "Introducción a redes con Mikrotik",
        "archivo": "0B0UxvnUHVKBcaDJUU3l5cjZkdU0",
        "categoria":"Trabajos de Alumnos",
        "tipo": "poster",
        "Autores": [
            {
                "Autor": "Tapia Diego  "
            },
            {
                "Autor": "Mayer Javier "
            },
            {
                "Autor": "Encinas Diego "
            },
            {
                "Autor": "Morales Martin "
            }
        ]
    },
    {
        "titulo": "IOT riesgos y oportunidades",
        "archivo": "0B0UxvnUHVKBcd2w5UEZYSGtycVk",
       "categoria":"Trabajos de Alumnos",
        "tipo": "poster",
        "Autores": [
            {
                "Autor": "Jorge Benitez "
            },
            {
                "Autor": "Melina Fellay "
            },
            {
                "Autor": "Juan Andrés Frigo "
            }
        ]
    },
    {
        "titulo": "La Utilización de la Informática y los Sistemas de Información en la Reducción de Papel en las Organizaciones",
        "archivo": "0B0UxvnUHVKBccWxxQTJoVG5TTXM",
         "categoria":"Trabajos de Alumnos",
        "tipo": "poster",
        "Autores": [
            {
                "Autor": "Santiago Anaya "
            },
            {
                "Autor": "Gastón Galbán "
            },
            {
                "Autor": "Lucas Saller "
            },
            {
                "Autor": "Sebastian Diaz Argentino "
            },
            {
                "Autor": "Ignacio Zullo Salvucci"
            },
            {
                "Autor": "Lucila Salmeron"
            }
        ]
    },
    {
        "titulo": "Las Cookies y la privacidad Consideraciones y recomendaciones",
        "archivo": "0B0UxvnUHVKBcY0otYzFzbDc0SEU",
        "categoria":"Trabajos de Alumnos",
        "tipo": "poster",
        "Autores": [
            {
                "Autor": "Luciano Bracco "
            },
            {
                "Autor": "Facundo Coto  "
            }
        ]
    },

{
        "titulo": "Las distintas utilizaciones de la interfaz cerebro computador",
        "archivo": "0B0UxvnUHVKBceHRQYVFLZ2QxMWc",
        "categoria":"Trabajos de Alumnos",
        "tipo": "poster",
        "Autores": [
            {
                "Autor": "Alejandro Chañi "
            },
            {
                "Autor": "Kevin Michelone"
            },
             {
                "Autor": "Juan Vergara"
            },
            {
                "Autor": "Matias Torelli"
            },
             {
                "Autor": "Nicolas Nardi"
            },
            {
                "Autor": "Nicolas Florian"
            }
        ]
 },


    {
        "titulo": "Librería de Multiprogramación para Arduino",
        "archivo": "0B0UxvnUHVKBcZ043WFZoQncteU0",
        "categoria":"Trabajos de Alumnos",
        "tipo": "poster",
        "Autores": [
            {
                "Autor": "Facundo Javier Gelatti  "
            }
        ]
    },
    {
        "titulo": "Los estudiantes universitarios y las TIC",
        "archivo": "0B0UxvnUHVKBcb0pZbjVFY3BnNGM",
        "categoria":"Trabajos de Docentes - Investigadores",
        "tipo": "poster",
        "Autores": [
            {
                "Autor": "Roberto D. Lamas "
            },
            {
                "Autor": "Claudio M. Perez Ibarra "
            },
            {
                "Autor": "Adelina García "
            }
        ]
    },
    {
        "titulo": "Lost in the Abysm",
        "archivo": "0B0UxvnUHVKBcVmxWVV9tVE04TlE",
        "categoria":"Trabajos de Alumnos",
        "tipo": "poster",
        "Autores": [
            {
                "Autor": "Lauro Cacciagioni  "
            },
            {
                "Autor": "Marcelo Vaquero  "
            },
            {
                "Autor": "Alejandro Sartorio  "
            }
        ]
    },
    {
        "titulo": "MASAA",
       "archivo":"0B0UxvnUHVKBcNkZQcU1tMVg3T0U",
        "categoria":"Trabajos de Docentes - Investigadores",
        "tipo": "poster",
        "Autores": [
            {
                "Autor": "Juan Carlos Calloni "
            },
            {
                "Autor": "Andrés Bianciotti  "
            },
            {
                "Autor": "Sergio Paez  "
            },
            {
                "Autor": "Eduardo Scarello  "
            },
            {
                "Autor": "Leandro Banchio "
            },
            {
                "Autor": "Juan Carlos Cuevas"
            }
        ]
    },
    {
        "titulo": "Matemática Discreta cursado b-learning para alumnos recursantes",
        "archivo": "0B0UxvnUHVKBcdVBKSlpXUFNMNFE",
        "categoria":"Trabajos de Docentes - Investigadores",
        "tipo": "poster",
        "Autores": [
            {
                "Autor": "Adelina García  "
            },
            {
                "Autor": "Roberto D. Lamas  "
            },
            {
                "Autor": "Verónica M. Torres  "
            }
        ]
    },
    {
        "titulo": "Meta-Framework de Arquitectura Empresarial ",
        "archivo": "0B0UxvnUHVKBcSktjdEdxY2k2UGM",
        "categoria":"Trabajos de Alumnos",
        "tipo": "poster",
        "Autores": [
            {
                "Autor": "Ing. Diego Tudury  "
            },
            {
                "Autor": "Ing. Pablo Antedomenico  "
            }
        ]
    },
    {
        "titulo": "MuniApp - Servicio de Ayuda Ciudadana",
        "archivo": "0B0UxvnUHVKBccmVDeVRPbHpnVGM",
        "categoria":"Trabajos de Alumnos",
        "tipo": "poster",
        "Autores": [
            {
                "Autor": "Gabriel Barrientos"
            },
            {
                "Autor": "Maximiliano Espeche"
            },
            {
                "Autor": "Emanuel Gomez"
            },
            {
                "Autor": "Sebastian Reverso"
            }
        ]
 },
 {
        "titulo": "Negocios orientados a dispositivos móviles y su implementación",
        "archivo": "0B0UxvnUHVKBcSml1TFJEVVBsdGs",
        "categoria":"Trabajos de Alumnos",
        "tipo": "poster",
        "Autores": [
            {
                "Autor": "Valentín Costa"
            },
            {
                "Autor": "Martín Cuba"
            },
             {
                "Autor": "David Lazbal"
            },
            {
                "Autor": "Diego Lonardi"
            },
             {
                "Autor": "Fernando Rodríguez Cora "
            },
            {
                "Autor": "Luciano Thoma "
            }
        ]
 },
    {
        "titulo": "OMNIA",
        "archivo": "0B0UxvnUHVKBcZWhKWkpqQVN0VFE",
        "categoria":"Trabajos de Alumnos",
        "tipo": "poster",
        "Autores": [
            {
                "Autor": "Brito Joel"
            },
            {
                "Autor": "Natalini Leandro "
            },
            {
                "Autor": "Zahradnicek Desirée  "
            },
            {
                "Autor": "Pérez Alegre Adriel  "
            },
            {
                "Autor":"Peirasso Evangelina "
            }
        ]
    },
    {
        "titulo": "Open Data",
        "archivo": "0B0UxvnUHVKBcRHIzUVhBNnBJT0E",
        "categoria":"Trabajos de Alumnos",
        "tipo": "poster",
        "Autores": [
            {
                "Autor": "Julián Ignacio Acosta  "
            },
            {
                "Autor": "Germán Asmus  "
            },
            {
                "Autor": "Silvana Belén García  "
            },
            {
                "Autor": "Facundo Rodríguez  "
            },
            {
                "Autor":"Alejandro Fabián Segovia "
            }
        ]
    },
    {
        "titulo": "Operationalization of the Architecture Principle “Partitioning, Encapsulation and Coupling”",
        "archivo": "0B0UxvnUHVKBcSDBRSjZZOFpyLVk”",
        "categoria":"Trabajos de Alumnos",
        "tipo": "poster",
        "Autores": [
            {
                "Autor": "Rivero Noelia Belén  "
            }
        ]
    },
    {
        "titulo": "Paper Construcción de una Aplicación de realidad mixta en la elaboración de recetas de cocina - CocinApp",
        "archivo": "0B0UxvnUHVKBcXzAwZGxDa2x3bGM",
        "categoria":"Trabajos de Alumnos",
        "tipo": "poster",
        "Autores": [
            {
                "Autor": "Cristian Hernán González "
            },
            {
                "Autor": "Martín Ángel Morrongiello  "
            },
            {
                "Autor": "Gabriel Andrés Castagno "
            },
            {
                "Autor": "Nicolás Di Vito "
            },
            {
                "Autor": "Gonzalo Iván Lucero  "
            },
            {
                "Autor": "Javier Ramírez  "
            }
        ]
    },
    {
        "titulo": "Perfiles e incumbencias de carreras de informática y sistemas de información en la Ciudad de Buenos Aires",
        "archivo": "0B0UxvnUHVKBcSUtiQnFCYk5xMnM",
        "categoria":"Trabajos de Alumnos",
        "tipo": "poster",
        "Autores": [
            {
                "Autor": "Victoria Lippolis  "
            },
            {
                "Autor": "Ronan Bio "
            },
            {
                "Autor": "Mariano De Luca "
            },
            {
                "Autor": "Marcos Donner "
            },
            {
                "Autor": "Elias Kim"
            },
            {
                "Autor": "Leonardo Maestri"
            }
        ]
    },
    {
        "titulo": "Plan Integral de Informática",
        "archivo": "0B0UxvnUHVKBcekJyRXdJdmZVUjQ",
        "categoria":"Trabajos de Docentes - Investigadores",
        "tipo": "poster",
        "Autores": [
            {
                "Autor": "Ricardo José Corbella  "
            }
        ]
    },
    {
        "titulo": "Pornografía infantil Marco legal y herramientas peer to peer",
        "archivo": "0B0UxvnUHVKBcNFh5ejg0aV81a28",
        "categoria":"Trabajos de Alumnos",
        "tipo": "poster",
        "Autores": [
            {
                "Autor": "Matías Nicolas Amor "
            }
        ]
    },
    {
        "titulo": "Predicción de Reelección Presidencial mediante Sistemas Inteligentes",
        "archivo": "0B0UxvnUHVKBcYmJrbEFvbVZST1k",
        "categoria":"Trabajos de Alumnos",
        "tipo": "poster",
        "Autores": [
            {
                "Autor": "Miguel Elias Arteaga Orozco  "
            },
            {
                "Autor": "Hernan Suzuki Son  "
            }
        ]
    },
    {
        "titulo": "Predicción de Tráfico en Redes Globales Multiprotocolo aplicando Redes Expertas Difusas",
        "archivo": "0B0UxvnUHVKBcZGtFSXU2UnBVbzQ",
        "categoria":"Trabajos de Alumnos",
        "tipo": "poster",
        "Autores": [
            {
                "Autor": "Paz Aldo Esteban  "
            },
            {
                "Autor": "Rivero Noelia Belén  "
            }
        ]
    },
    {
        "titulo": "PREGUTNADOS Una herramienta de soporte al aprendizaje",
        "archivo": "0B0UxvnUHVKBcajRUYkxyNjRCUHc",
        "categoria":"Trabajos de Alumnos",
        "tipo": "poster",
        "Autores": [
            {
                "Autor": "Federico Hauque  "
            },
            {
                "Autor": "Germán Saudejaud"
        }]
    },

{
        "titulo": "Propuesta de un Catálogo de Patrones para el Análisis y Diseño de la Interfaz de Groupware",
        "archivo": "0B0UxvnUHVKBcNUo2QVN2YnAwdDg",
        "categoria":"Trabajos de Alumnos",
        "tipo": "poster",
        "Autores": [
            {
                "Autor": "Noelia Alejandra Yolde Deppen"
            },
            {
                "Autor": "Mabel del Valle Sosa"
            },
            {
                "Autor":"Ivanna Paola Maldonado "
            }
        ]
 },

    {
        "titulo": "Propuesta para la concientización del consumo responsable del agua usando tecnologías ",
        "archivo": "0B0UxvnUHVKBcdDNhbFVGV0R3eVU",
        "categoria":"Trabajos de Alumnos",
        "tipo": "poster",
        "Autores": [
            {
                "Autor": "Laura Romina Aristegui  "
            }
        ]
    },
    {
        "titulo": "Realtime Volume Render en Videojuegos",
        "archivo": "0B0UxvnUHVKBcQ1JKOUdZN2FmUjg",
        "categoria":"Trabajos de Docentes - Investigadores",
        "tipo": "poster",
        "Autores": [
            {
                "Autor": "Ortiz Edgar  "
            },
            {
                "Autor": "Banquiero Mariano  "
            },
            {
                "Autor": "Rossi Bibiana"
            }
        ]
    },
    {
        "titulo": "Redes Definidas por Software",
        "archivo": "0B0UxvnUHVKBcbVExcTE2ZnpnUEE",
        "categoria":"Trabajos de Alumnos",
        "tipo": "poster",
        "Autores": [
            {
                "Autor": "Benitez Gabriel  "
            },
            {
                "Autor": "Morales Martin "
            },
            {
                "Autor": "Encinas Diego "
            }
        ]
    },
    {
        "titulo": "Redes neuronales no supervisadas competitivas entrenadas mediante algoritmos genéticos ",
        "archivo": "0B0UxvnUHVKBcNV9YSFVWYzRZSnM",
          "categoria":"Trabajos de Alumnos",
        "tipo": "poster",
        "Autores": [
            {
                "Autor": "Merlo Mateo  "
            },
            {
                "Autor": "Pecchio Lucas  "
            },
            {
                "Autor": "Sánchez Tadeo  "
            }
        ]
    },

{
        "titulo": "Riesgos del uso de las redes sociales",
        "archivo": "0B0UxvnUHVKBcYndab2NJVHRlaGs",
        "categoria":"Trabajos de Alumnos",
        "tipo": "poster",
        "Autores": [
            {
                "Autor": "Matias Baghdassarian"
            },
            {
                "Autor": "Nicolas Calle"
            },
            {
                "Autor": "Sebastian Guozden"
            },
            {
                "Autor": "Tomas Gorkin"
            },
            {
                "Autor": "Pablo Monti"
            }
        ]
 },
 {
        "titulo": "secatt Herramienta online para asistir a la correspondencia entre Patrones de Ataque y de Seguridad",
        "archivo": "0B0UxvnUHVKBcaURHNUtpRWZQTmM",
        "categoria":"Trabajos de Alumnos",
        "tipo": "poster",
        "Autores": [
            {
                "Autor": "Ignacio Ramos "
            },
            {
                "Autor": "Sofia Lottersberger "
            },
            {
                "Autor":"Nicolas J. Guimar "
            }
        ]
 },



    {
        "titulo": "Seguimiento de Pacientes con Litiasis Renal – UTN FRT",
        "archivo": "0B0UxvnUHVKBcZ25TVlB5a2FmbXM",
        "categoria":"Trabajos de Alumnos",
        "tipo": "poster",
        "Autores": [
            {
                "Autor": "José Cardozo "
            },
            {
                "Autor": "Vicente Chibilisco "
            },
            {
                "Autor": "María Molina "
            },
            {
                "Autor": "María Nieva "
            }
        ]
    },
    {
        "titulo": "Seguridad de los datos en las redes sociales ",
        "archivo": "0B0UxvnUHVKBcYUJVTDAxYUJFYmM",
        "categoria":"Trabajos de Alumnos",
        "tipo": "poster",
        "Autores": [
            {
                "Autor": "Juan Pablo Marcialis "
            },
            {
                "Autor": "Joao Baptista"
            },
            {
                "Autor": "Luciano Mansilla "
            },
            {
                "Autor": "Gonzalo Fernandez"
            }
        ]
 },
    {
        "titulo": "SIAC  Sistema de Información de Alertas y Conciencia Ciudadana",
        "archivo": "0B0UxvnUHVKBcRjdXY1RieW1KNkk",
        "categoria":"Trabajos de Alumnos",
        "tipo": "poster",
        "Autores": [
            {
                "Autor": "Lucas de la Fuente  "
            },
            {
                "Autor": "Marcelo Belbey  "
            },
            {
                "Autor": "Fabrizio Appiano  "
            },
            {
                "Autor": "Diego Tello  "
            }
        ]
    },
    {
        "titulo": "Siempre Contigo ",
        "archivo": "0B0UxvnUHVKBccFR6XzBUdnRQS00",
         "categoria":"Trabajos de Alumnos",
        "tipo": "poster",
        "Autores": [
            {
                "Autor": "Reyes, Jorge L. "
            },
            {
                "Autor": "Brandan, Marcelo "
            },
            {
                "Autor": "Rueda, Julio G. "
            },
            {
                "Autor": "Arias, Marina "
            }
        ]
    },
    {
        "titulo": "Simulación Acotada de Procesadores ",
        "archivo": "0B0UxvnUHVKBccFR6XzBUdnRQS00",
         "categoria":"Trabajos de Alumnos",
        "tipo": "poster",
        "Autores": [
            {
                "Autor": "Tomás Juárez"
            },
            {
                "Autor": "Guillermo Pacheco "
            }
        ]
    },
    {
        "titulo": "Sistema de control inteligente de patentes de vehículos para la Policía a través de una aplicación móvil",
        "archivo": "0B0UxvnUHVKBcTDNXelNuQWNqWWc",
        "categoria":"Trabajos de Alumnos",
        "tipo": "poster",
        "Autores": [
            {
                "Autor": "Seiyu Ricardo Higa Tamashiro  "
            },
            {
                "Autor": "Spalletti Mauricio Gabriel    "
            }
        ]
    },
    {
        "titulo": "Sistema de semaforización inteligente",
        "archivo": "0B0UxvnUHVKBcQVNjOEtGclJwYTg",
        "categoria":"Trabajos de Alumnos",
        "tipo": "poster",
        "Autores": [
            {
                "Autor": "Bonessi, Santiago "
            },
            {
                "Autor": "Cargnelutti, Renato "
            },
            {
                "Autor": "Griguol, Agustin "
            },
            {
                "Autor": "Ortigoza, Matias "
            },
            {
                "Autor":"Somadossi, Andrés"
            }
        ]
    },
    {
        "titulo": "Sistema Experto y Lógica Difusa Aplicadas en la Clasificación y Traslado de Basura para Reciclaje",
        "archivo": "0B0UxvnUHVKBcUTJnODcybjloRWs",
        "categoria":"Trabajos de Alumnos",
        "tipo": "poster",
        "Autores": [
            {
                "Autor": "Melisa Anabel Jiménez Galarza "
            },
            {
                "Autor": "Selma Muriel Jiménez Galarza  "
            },
            {
                "Autor": "Maria Emilia Lavenia  "
            },
            {
                "Autor": "Alejandra Paola Quispe Mendez "
            }
        ]
    },
    {
        "titulo": "Smart Aqua",
        "archivo": "0B0UxvnUHVKBcTW9yd1VXRjhZUTg",
        "categoria":"Trabajos de Alumnos",
        "tipo": "poster",
        "Autores": [
            {
                "Autor": "Barbesini, Nicolás "
            },
            {
                "Autor": "Ledesma, Nahuel "
            },
            {
                "Autor": "Delgado, Fabricio "
            },
            {
                "Autor": "Olivera, Braian "
            }
        ]
    },
{
        "titulo": "Snapchat Unicidad y Control",
        "archivo": "0B0UxvnUHVKBcNWRwSmR0bkVLLWc",
        "categoria":"Trabajos de Alumnos",
        "tipo": "poster",
        "Autores": [
            {
                "Autor": "Andini, Micaela "
            },
            {
                "Autor": "Carrera. Katherine"
            },
            {
                "Autor": "Lucchelli, Sophia"
            },
            {
                "Autor": "Ramirez, Naimid"
            }
        ]
 },
 {
        "titulo": "Tecnologías aplicadas al tratamiento de discapacidades motoras ",
        "archivo": "0B0UxvnUHVKBcT3JpZGg1UWdjam8",
        "categoria":"Trabajos de Alumnos",
        "tipo": "poster",
        "Autores": [
            {
                "Autor": "Galeano Lucas"
            },
            {
                "Autor": "Federico Macias"
            },
            {
                "Autor": "Gianpier Yupanqui"
            },
            {
                "Autor": "Kevin Brian"
            },
            {
                "Autor": "Agustín Martínez"
            }
        ]
 },


    {
        "titulo": "Tipos de ataques, técnicas y herramientas utilizadas para vulnerar aplicaciones web",
        "archivo": "0B0UxvnUHVKBccm56NVR6b2w2ZTQ",
         "categoria":"Trabajos de Docentes - Investigadores",
        "tipo": "poster",
        "Autores": [
            {
                "Autor": "Cuevas, Juan Carlos "
            },
            {
                "Autor": "Muñoz, Roberto "
            },
            {
                "Autor": "Gibellini, Fabian A. "
            },
            {
                "Autor": "Parisi, Germán "
            },
             {
                "Autor": "Zea Cárdenas, Milagros"
            },
            {
                "Autor": "Barrionuevo, Diego"
            }
        ]
    },
    {
        "titulo": "Un estudio de simulación como aporte de información para la toma de decisiones organizacionales",
        "archivo": "0B0UxvnUHVKBcUTV6a3RBbXlCcXc",
        "categoria":"Trabajos de Alumnos",
        "tipo": "poster",
        "Autores": [
            {
                "Autor": "Gonzalo Weiss  "
            }
        ]
    },
    {
        "titulo": "Un nuevo Método para clustering de tweets basado en métodos de ensambles y técnicas de hashing",
        "archivo": "0B0UxvnUHVKBcaTJRQWUwVENWSnM",
        "categoria":"Trabajos de Docentes - Investigadores",
        "tipo": "poster",
        "Autores": [
            {
                "Autor": "Matías E. Gentile  "
            },
            {
                "Autor": "Bruno J. Varani "
            },
            {
                "Autor": "Eduardo Amar "
            },
            {
                "Autor": "Cristian Bigatti "
            },
              {
                "Autor": "M. Cecilia Kraiselburd"
            },
            {
                "Autor": "Fabricio Neirotti"
            },
              {
                "Autor": "Juan M. Moine"
            }
        ]
    },
    {
        "titulo": "Un proxy UDT para un sistema de virtualización distribuido ",
        "archivo": "0B0UxvnUHVKBcYTA2bGlMNmhMVUU",
        "categoria":"Trabajos de Alumnos",
        "tipo": "poster",
        "Autores": [
            {
                "Autor": "Guillermo Jacob  "
            },
            {
                "Autor": "Matías Sequeira  "
            }
        ]
    },
    {
        "titulo": "Una implementación sobre Cloudera ",
        "archivo": "0B0UxvnUHVKBcbWZ0Y3hORUZvTG8",
        "categoria":"Trabajos de Docentes - Investigadores",
        "tipo": "poster",
        "Autores": [
            {
                "Autor": "S. Retamar "
            },
            {
                "Autor": "L. Ramos  "
            },
            {
                "Autor": "N. Herrera "
            },
            {
                "Autor": "N. Rapesta "
            },
            {
                "Autor": "J.P. Nuñez"
            },
            {
                "Autor": "P. Cristaldo "
            },
            {
                "Autor": "A. De Battista"
            }
        ]
    },
    {
        "titulo": "TurImag Sistema de Información Turística Mediante Reconocimiento Automático de Imágenes",
        "archivo": "0B0UxvnUHVKBcQkRESlVncnh4TVE",
        "categoria":"Trabajos de Alumnos",
        "tipo": "poster",
        "Autores": [
            {
                "Autor": "Ricardo Martin Llobet  "
            },
            {
                "Autor": "Cristian Alberto Marcos  "
            },
            {
                "Autor": "Marcelo Alejandro Tosini  "
            },
            {
                "Autor": "Julio Esteban Kun  "
            }
        ]
    },
    {
        "titulo": "Vulnerabilidades del internet de las cosas y delitos derivados",
        "archivo": "0B0UxvnUHVKBcS1A4YTBzMEY1MjA",
        "categoria":"Trabajos de Alumnos",
        "tipo": "poster",
        "Autores": [
            {
                "Autor": "Fabio Emanuel Gómez Castro"
            },
            {
                "Autor": "Aldo Guido Arzelan "
            }
        ]
    },
    {
        "titulo": "Wiree - Propuesta de una Metodología de Recuperación de Información Web Eficaz y Eficiente para un Dominio Específico",
        "archivo": "0B0UxvnUHVKBcTlNIVTR5eC0zSVU",
        "categoria":"Trabajos de Docentes - Investigadores",
        "tipo": "poster",
        "Autores": [
            {
                "Autor": "María Romagnano"
            }
        ]
    },
     {
        "titulo": "Desarrollo de aplicaciones de comercio electrónico con servicios de la nube computacional",
        "archivo": "0B0UxvnUHVKBcdGtKVEJvcU9GSTQ",
        "categoria":"Trabajos de Docentes - Investigadores",
        "tipo": "poster",
        "Autores": [
            {
                "Autor": "Rodrigo Basualdo"
            },
	        {
                "Autor": "Esteban Massuh"
            },
            {
                "Autor": "Federico Baroni"
            },
	        {
                "Autor": "Rosana Portillo"
            }
        ]
    },
     {
        "titulo": "Deserción Universitaria: Validación de Patrones Relacionales en los Alumnos de Primer Año",
        "archivo": "0B0UxvnUHVKBcci1HLWFqZ1lSVmM",
        "categoria":"Trabajos de Docentes - Investigadores",
        "tipo": "poster",
        "Autores": [
            {
                "Autor": "Mariana Falco"
            },
	    {
                "Autor": "Sergio A. Antonini"
            },
            {
                "Autor": "Romina M. Istvan"
            }
        ]
    },
     {
        "titulo": "Evaluando la Calidad de Uso en una Aplicación Web de Gobierno Electrónic",
        "archivo": "0B0UxvnUHVKBcQW80eUloTWM4dVE",
        "categoria":"Trabajos de Docentes - Investigadores",
        "tipo": "poster",
        "Autores": [
            {
                "Autor": "Marcelo Castro "
            },
	        {
                "Autor": "David Sánchez Rivero"
            },
            {
                "Autor": "Alejandro Vargas"
            },
	        {
                "Autor": "José Farfán"
            },
            {
                "Autor": "Elizabeth Reinoso"
            },
	        {
                "Autor": "María Aparicio"
            },
            {
                "Autor": "Fabiana Aragón"
            },
	        {
                "Autor": "José Zapana"
            },
            {
                "Autor": "Andrea Cándido"
            },
	        {
                "Autor": "Liliana Cazón"
            }
        ]
    },
    {
        "titulo": "Hipertension Arterial - Modelos de programacion lineal aplicados a la Dieta Dash",
        "archivo": "0B0UxvnUHVKBcOF83X0pmRl9QSWM",
        "categoria":"Trabajos de Alumnos",
        "tipo": "poster",
        "Autores": [
            {
                "Autor": "Federico Javier Gramajo "
            }
        ]
    },
    {
        "titulo": "Representación de Espacios Indoor utilizando la Herramienta de Desarrollo de Metamodelos ADOxx",
        "archivo": "0B0UxvnUHVKBcaWJKUm9LMExlSE0",
        "categoria":"Trabajos de Alumnos",
        "tipo": "poster",
        "Autores": [
            {
                "Autor": "Karen Poch"
            },
	         {
                "Autor": "Paula Rispoli"
            }
        ]
    },
    {
        "titulo": "Sistema de monitoreo de alcoholemia - SMA",
        "archivo": "0B0UxvnUHVKBcZFV2VmgzWU5pNXM",
        "categoria":"Trabajos de Alumnos",
        "tipo": "poster",
        "Autores": [
            {
                "Autor": "Marcos Luis Senatra"
            },
	        {
                "Autor": "Gonzalo David Vicino "
            },
            {
                "Autor":"Jorge Luis Favier"
            }
        ]
    },
     {
        "titulo": "Sistemas de Información para la minería de datos georeferenciada en ecología urbana Perros callejeros como caso de estudio",
        "archivo": "0B0UxvnUHVKBcZkZKZVNPU3BZMms",
        "categoria":"Trabajos de Docentes - Investigadores",
        "tipo": "poster",
        "Autores": [
            {
                "Autor": "Luis Ramos "
            },
	        {
                "Autor": "Diego Procopio "
            },
            {
                "Autor": "Marta Lasso "
            },
	        {
                "Autor": "Ma. Eugenia de San Pedro "
            }
        ]
    },
     {
        "titulo": "Student Play: un Módulo Educativo de Agent SocialMetric",
        "archivo": "0B0UxvnUHVKBcV25OQWQxLXJ0WXc",
        "categoria":"Trabajos de Docentes - Investigadores",
        "tipo": "poster",
        "Autores": [
            {
                "Autor": "Antonieta Kuz"
            },
	        {
                "Autor": "Mariana Falco"
            },
            {
                "Autor": "Roxana S. Giandini"
            },
	        {
                "Autor": "Francisco Castellini"
            }
        ]
    }


]